pandas_accumulate/__init__.py
pandas_accumulate-0.1.0.dist-info/LICENSE
pandas_accumulate-0.1.0.dist-info/WHEEL
pandas_accumulate-0.1.0.dist-info/METADATA
pandas_accumulate-0.1.0.dist-info/RECORD
