Metadata-Version: 2.1
Name: pandas-accumulate
Version: 0.1.0
Summary: Accumulate Pandas series
Author-email: Eike von Seggern <eike@vonseggern.space>
Requires-Python: >=3.8
Classifier: License :: OSI Approved :: MIT License
Requires-Dist: numpy
Requires-Dist: pandas
Requires-Dist: pytest >=7.2.1 ; extra == "test"
Provides-Extra: test
